mini_mock_server/__init__.py
mini_mock_server/main.py
mini_mock_server/schemas.py
mini_mock_server/file_processor/__init__.py
mini_mock_server/file_processor/json_file.py
mini_mock_server/http_server/__init__.py
mini_mock_server/http_server/request.py
mini_mock_server/http_server/response.py
mini_mock_server/http_server/server.py
mini_mock_server/validators/__init__.py
mini_mock_server/validators/route/__init__.py
mini_mock_server/validators/route/method.py
mini_mock_server/validators/route/response.py
mini_mock_server/validators/route/validator.py
tests/__init__.py
tests/file_processor/__init__.py
tests/file_processor/test_json_file.py
tests/http_server/__init__.py
tests/http_server/test_request.py
tests/http_server/test_server.py
tests/validators/__init__.py
tests/validators/test_response.py
tests/validators/test_route_validator.py
mini_mock_server-0.0.28.dist-info/METADATA
mini_mock_server-0.0.28.dist-info/WHEEL
mini_mock_server-0.0.28.dist-info/entry_points.txt
mini_mock_server-0.0.28.dist-info/top_level.txt
mini_mock_server-0.0.28.dist-info/RECORD
